processing_images/__init__.py
processing_images/processing/__init__.py
processing_images/processing/combination.py
processing_images/processing/transformation.py
processing_images/utils/__init__.py
processing_images/utils/io.py
processing_images/utils/plot.py
processing_images-0.0.1.dist-info/METADATA
processing_images-0.0.1.dist-info/WHEEL
processing_images-0.0.1.dist-info/top_level.txt
processing_images-0.0.1.dist-info/RECORD
