Metadata-Version: 2.1
Name: processing-images
Version: 0.0.1
Summary: Image color processor
Home-page: https://github.com/83Rafa/image-color-merger.git
Author: 83Rafa
Author-email: elfaramail@gmail.com
License: UNKNOWN
Platform: UNKNOWN
Requires-Python: >=3.8
Requires-Dist: scikit-image (>=0.16.1)
Requires-Dist: matplotlib
Requires-Dist: numpy
